runqy_task/__init__.py
runqy_task/decorator.py
runqy_task/runner.py
runqy_task-0.1.0.dist-info/LICENSE
runqy_task-0.1.0.dist-info/METADATA
runqy_task-0.1.0.dist-info/WHEEL
runqy_task-0.1.0.dist-info/top_level.txt
runqy_task-0.1.0.dist-info/RECORD
