Metadata-Version: 2.1
Name: runqy-task
Version: 0.1.0
Summary: Python SDK for runqy-worker tasks
Author: Publikey
Project-URL: Repository, https://github.com/Publikey/runqy-python
Project-URL: Issues, https://github.com/Publikey/runqy-python/issues
Keywords: task-queue,distributed,worker,redis,async
Classifier: Development Status :: 4 - Beta
Classifier: Intended Audience :: Developers
Classifier: License :: OSI Approved :: MIT License
Classifier: Programming Language :: Python :: 3
Classifier: Programming Language :: Python :: 3.8
Classifier: Programming Language :: Python :: 3.9
Classifier: Programming Language :: Python :: 3.10
Classifier: Programming Language :: Python :: 3.11
Classifier: Programming Language :: Python :: 3.12
Classifier: Topic :: Software Development :: Libraries :: Python Modules
Requires-Python: >=3.8
License-File: LICENSE
